codewit_semeru/__init__.py
codewit_semeru/backend/model.py
codewit_semeru/backend/pipeline.py
codewit_semeru/backend/pipeline_store.py
codewit_semeru/frontend/layout.py
codewit_semeru/frontend/server.py
codewit_semeru/frontend/assets/styles.css
codewit_semeru-0.1.4.dist-info/METADATA
codewit_semeru-0.1.4.dist-info/WHEEL
codewit_semeru-0.1.4.dist-info/licenses/LICENSE
codewit_semeru-0.1.4.dist-info/RECORD
