Metadata-Version: 2.1
Name: codewit_semeru
Version: 0.1.4
Summary: Code What-If-Tool
Project-URL: Homepage, https://github.com/WM-SEMERU/csci-435_what_if_tool
Project-URL: Bug Tracker, https://github.com/WM-SEMERU/csci-435_what_if_tool/issues
Author-email: Ignat Miagkov <iamiagkov@wm.edu>, Duke Tran <dtran@wm.edu>, Eli Svoboda <essvoboda@wm.edu>
License-File: LICENSE
Classifier: License :: OSI Approved :: MIT License
Classifier: Operating System :: OS Independent
Classifier: Programming Language :: Python :: 3
Requires-Python: >=3.8
Requires-Dist: jupyter-dash
Requires-Dist: pandas
Requires-Dist: python-dotenv
Requires-Dist: torch
Requires-Dist: transformers
